README.rst
setup.cfg
setup.py
bin/oneid-cli
src/oneID_cli.egg-info/PKG-INFO
src/oneID_cli.egg-info/SOURCES.txt
src/oneID_cli.egg-info/dependency_links.txt
src/oneID_cli.egg-info/requires.txt
src/oneID_cli.egg-info/top_level.txt
src/oneid_cli/__init__.py
src/oneid_cli/cli_handler.py
src/oneid_cli/constants.py
src/oneid_cli/session.py
src/oneid_cli/util.py
src/oneid_cli/config_file/__init__.py
src/oneid_cli/config_file/base_loader.py
src/oneid_cli/config_file/context.py
src/oneid_cli/config_file/json_loader.py
src/oneid_cli/config_file/legacy_loader.py
src/oneid_cli/config_file/yaml_loader.py
src/oneid_cli/key_managers/__init__.py
src/oneid_cli/key_managers/base.py
src/oneid_cli/key_managers/legacy.py
src/oneid_cli/key_managers/ntdi.py
src/oneid_cli/services/__init__.py
src/oneid_cli/services/base.py
src/oneid_cli/services/configure.py
src/oneid_cli/services/create_project.py
src/oneid_cli/services/list_projects.py
src/oneid_cli/services/provision.py
src/oneid_cli/services/revoke.py
src/oneid_cli/services/show.py
src/oneid_cli/services/unrevoke.py