Metadata-Version: 1.1
Name: oneID-cli
Version: 1.0.35
Summary: A command line interface for the Neustar Trusted Identity (TDI) Core
Home-page: https://www.oneID.com
Author: Neustar Inc.
Author-email: support@oneID.com
License: Apache License, Version 2.0
Keywords: TDI IoT Identity Authentication
Platform: UNKNOWN
Classifier: Development Status :: 4 - Beta
Classifier: Intended Audience :: Developers
Classifier: License :: OSI Approved :: Apache Software License
Classifier: Natural Language :: English
Classifier: Operating System :: MacOS :: MacOS X
Classifier: Operating System :: POSIX
Classifier: Operating System :: POSIX :: BSD
Classifier: Operating System :: POSIX :: Linux
Classifier: Topic :: Security :: Cryptography
Classifier: Programming Language :: Python :: 2.7
Classifier: Programming Language :: Python :: 3.4
Classifier: Programming Language :: Python :: 3.5
Classifier: Programming Language :: Python :: 3.6
